streamlit/__init__.py
streamlit/__main__.py
streamlit/auth_util.py
streamlit/cli_util.py
streamlit/column_config.py
streamlit/config.py
streamlit/config_option.py
streamlit/config_util.py
streamlit/cursor.py
streamlit/dataframe_util.py
streamlit/delta_generator.py
streamlit/delta_generator_singletons.py
streamlit/deprecation_util.py
streamlit/development.py
streamlit/emojis.py
streamlit/env_util.py
streamlit/error_util.py
streamlit/errors.py
streamlit/file_util.py
streamlit/git_util.py
streamlit/logger.py
streamlit/material_icon_names.py
streamlit/net_util.py
streamlit/platform.py
streamlit/py.typed
streamlit/source_util.py
streamlit/starlette.py
streamlit/string_util.py
streamlit/temporary_directory.py
streamlit/time_util.py
streamlit/type_util.py
streamlit/url_util.py
streamlit/user_info.py
streamlit/util.py
streamlit/version.py
streamlit/commands/__init__.py
streamlit/commands/echo.py
streamlit/commands/execution_control.py
streamlit/commands/logo.py
streamlit/commands/navigation.py
streamlit/commands/page_config.py
streamlit/components/__init__.py
streamlit/components/lib/__init__.py
streamlit/components/lib/local_component_registry.py
streamlit/components/types/__init__.py
streamlit/components/types/base_component_registry.py
streamlit/components/types/base_custom_component.py
streamlit/components/v1/__init__.py
streamlit/components/v1/component_arrow.py
streamlit/components/v1/component_registry.py
streamlit/components/v1/components.py
streamlit/components/v1/custom_component.py
streamlit/components/v2/__init__.py
streamlit/components/v2/component_definition_resolver.py
streamlit/components/v2/component_file_watcher.py
streamlit/components/v2/component_manager.py
streamlit/components/v2/component_manifest_handler.py
streamlit/components/v2/component_path_utils.py
streamlit/components/v2/component_registry.py
streamlit/components/v2/get_bidi_component_manager.py
streamlit/components/v2/manifest_scanner.py
streamlit/components/v2/presentation.py
streamlit_nightly-1.53.2.dev20260131.dist-info/METADATA
streamlit_nightly-1.53.2.dev20260131.dist-info/WHEEL
streamlit_nightly-1.53.2.dev20260131.dist-info/entry_points.txt
streamlit_nightly-1.53.2.dev20260131.dist-info/top_level.txt
streamlit_nightly-1.53.2.dev20260131.dist-info/RECORD
